an_envfilemanager/__init__.py
an_envfilemanager/envfilemanager.py
an_envfilemanager-0.1.0.dist-info/LICENSE
an_envfilemanager-0.1.0.dist-info/METADATA
an_envfilemanager-0.1.0.dist-info/WHEEL
an_envfilemanager-0.1.0.dist-info/top_level.txt
an_envfilemanager-0.1.0.dist-info/RECORD
