Metadata-Version: 2.2
Name: an_envfilemanager
Version: 0.1.0
Summary: A package for an_envfilemanager.
Home-page: https://github.com/Atsushi888/Atsushi888
Author: Atsushi888
Author-email: Atsushi888 <vtgrotxu@gmail.com>
Project-URL: Homepage, https://github.com/Atsushi888/an_envfilemanager
Project-URL: Repository, https://github.com/Atsushi888/an_envfilemanager
Requires-Python: >=3.6
License-File: LICENSE
Requires-Dist: an_DebugHelper
Dynamic: author
Dynamic: home-page
Dynamic: requires-python
